pydapters/__init__.py
pydapters/base.py
pydapters/registry.py
pydapters-0.0.1.dist-info/LICENSE
pydapters-0.0.1.dist-info/METADATA
pydapters-0.0.1.dist-info/WHEEL
pydapters-0.0.1.dist-info/top_level.txt
pydapters-0.0.1.dist-info/RECORD
